pgm_reader/__init__.py
pgm_reader/pgm_reader.py
pgm_reader-0.0.1.dist-info/LICENSE.md
pgm_reader-0.0.1.dist-info/METADATA
pgm_reader-0.0.1.dist-info/WHEEL
pgm_reader-0.0.1.dist-info/top_level.txt
pgm_reader-0.0.1.dist-info/RECORD
