Metadata-Version: 2.1
Name: pgm-reader
Version: 0.0.1
Summary: A Python package for reading pgm files
Home-page: https://github.com/BDEvan5/pgm
Author: Benjamin Evans
Author-email: 19811799@sun.ac.za
License: UNKNOWN
Platform: UNKNOWN
Classifier: Programming Language :: Python :: 3
Classifier: License :: OSI Approved :: MIT License
Classifier: Operating System :: OS Independent
Requires-Python: >=3.6
